Controller/IOController/clock_divider.v
module clock_divider(
    sysclk, 		// System Clock Input 100 Mhz
    sysclkfreq,
    divclkfreq,
    divclk);

    input [63:0] sysclkfreq;
    input [63:0] divclkfreq;
    input sysclk;

    output divclk;

    wire[64:0] CounterLimit;
    reg divided_clk = 0;
    reg[64:0] counter = 0;
    
    assign CounterLimit = (sysclkfreq / (2 * divclkfreq)) - 1;
    
    always @(posedge sysclk) begin
       if(counter < CounterLimit)
           counter <= counter + 1;
       else begin
           counter <= 0;    
           divided_clk <= ~divided_clk;
       end
    end

    assign divclk = divided_clk;
    
endmodule

Controller/IOController/InputController.v
module InputController(key_interrupt, jump_key, frame_rt_clk, sysclk, reset);

    input frame_rt_clk, sysclk, reset, jump_key;
    output key_interrupt;

    // reads from different registers at frame rate, compares contents

    reg key_interrupt_reg = 0;

    always @(posedge frame_rt_clk or posedge reset) begin
        if(reset) begin
            key_interrupt_reg <= 0;
        end else begin
            if (jump_key) begin
                key_interrupt_reg <= 1;
            end
        end
    end

    // turns off key_interrupt_reg as soon as possible (1 sys clock cycle after the frame rate rises)
    // so that only one interrupt instruction is sent to CPU

    always @(negedge sysclk) begin
        if (key_interrupt_reg) begin
            key_interrupt_reg <= 0;
        end
    end

    assign key_interrupt = key_interrupt_reg;

endmodule

Controller/IOController/InputControllerTB.v
`timescale 1ns/100ps
module InputControllerTB;

    // module inputs
    reg clock = 0;
    reg jump = 1;

    // output
    wire frame_rate_clk, key_interrupt;

    // definitions

    localparam MHz = 1000000;
    localparam SYSTEM_FREQ = 100*MHz; // System clock frequency

    localparam GAME_FRAME_RT = 10*MHz;

    InputController input_controller(.key_interrupt(key_interrupt), .jump_key(jump),
                                    .frame_rt_clk(frame_rate_clk), .sysclk(clock),
                                    .reset(1'b0));

    clock_divider frame_rate_clock_divider(.divclk(frame_rate_clk), .divclkfreq(GAME_FRAME_RT),
                                           .sysclk(clock), .sysclkfreq(SYSTEM_FREQ));

	integer i = 0;

	initial begin

        @(posedge clock);

        begin
            for (i = 0; i < 10000000; i = i + 1) begin

            end

            @(posedge clock);
		end

        $dumpfile("InputControllerTB.vcd");
        // Module to capture and what level, 0 means all wires
        $dumpvars(0, InputControllerTB);

		#1000;
		$finish;
	end

    always
    	#10 clock = !clock;

endmodule

InputControllerTB.vcd
$date
	Sun Nov 14 11:56:19 2021
$end
$version
	Icarus Verilog
$end
$timescale
	100ps
$end
$scope module InputControllerTB $end
$var wire 1 ! key_interrupt $end
$var wire 1 " frame_rate_clk $end
$var reg 1 # clock $end
$var reg 1 $ jump $end
$var integer 32 % i [31:0] $end
$scope module frame_rate_clock_divider $end
$var wire 1 " divclk $end
$var wire 64 & divclkfreq [63:0] $end
$var wire 1 # sysclk $end
$var wire 64 ' sysclkfreq [63:0] $end
$var wire 65 ( CounterLimit [64:0] $end
$var reg 65 ) counter [64:0] $end
$var reg 1 * divided_clk $end
$upscope $end
$scope module input_controller $end
$var wire 1 " frame_rt_clk $end
$var wire 1 $ jump_key $end
$var wire 1 ! key_interrupt $end
$var wire 1 + reset $end
$var wire 1 # sysclk $end
$var reg 1 , key_interrupt_reg $end
$upscope $end
$upscope $end
$enddefinitions $end
#300
$dumpvars
0,
0+
0*
b10 )
b100 (
b101111101011110000100000000 '
b100110001001011010000000 &
b100110001001011010000000 %
1$
1#
0"
0!
$end
#400
0#
#500
b11 )
1#
#600
0#
#700
b100 )
1#
#800
0#
#900
1!
1,
1"
1*
b0 )
1#
#1000
0!
0,
0#
#1100
b1 )
1#
#1200
0#
#1300
b10 )
1#
#1400
0#
#1500
b11 )
1#
#1600
0#
#1700
b100 )
1#
#1800
0#
#1900
0"
0*
b0 )
1#
#2000
0#
#2100
b1 )
1#
#2200
0#
#2300
b10 )
1#
#2400
0#
#2500
b11 )
1#
#2600
0#
#2700
b100 )
1#
#2800
0#
#2900
1!
1,
1"
1*
b0 )
1#
#3000
0!
0,
0#
#3100
b1 )
1#
#3200
0#
#3300
b10 )
1#
#3400
0#
#3500
b11 )
1#
#3600
0#
#3700
b100 )
1#
#3800
0#
#3900
0"
0*
b0 )
1#
#4000
0#
#4100
b1 )
1#
#4200
0#
#4300
b10 )
1#
#4400
0#
#4500
b11 )
1#
#4600
0#
#4700
b100 )
1#
#4800
0#
#4900
1!
1,
1"
1*
b0 )
1#
#5000
0!
0,
0#
#5100
b1 )
1#
#5200
0#
#5300
b10 )
1#
#5400
0#
#5500
b11 )
1#
#5600
0#
#5700
b100 )
1#
#5800
0#
#5900
0"
0*
b0 )
1#
#6000
0#
#6100
b1 )
1#
#6200
0#
#6300
b10 )
1#
#6400
0#
#6500
b11 )
1#
#6600
0#
#6700
b100 )
1#
#6800
0#
#6900
1!
1,
1"
1*
b0 )
1#
#7000
0!
0,
0#
#7100
b1 )
1#
#7200
0#
#7300
b10 )
1#
#7400
0#
#7500
b11 )
1#
#7600
0#
#7700
b100 )
1#
#7800
0#
#7900
0"
0*
b0 )
1#
#8000
0#
#8100
b1 )
1#
#8200
0#
#8300
b10 )
1#
#8400
0#
#8500
b11 )
1#
#8600
0#
#8700
b100 )
1#
#8800
0#
#8900
1!
1,
1"
1*
b0 )
1#
#9000
0!
0,
0#
#9100
b1 )
1#
#9200
0#
#9300
b10 )
1#
#9400
0#
#9500
b11 )
1#
#9600
0#
#9700
b100 )
1#
#9800
0#
#9900
0"
0*
b0 )
1#
#10000
0#
#10100
b1 )
1#
#10200
0#
#10300
b10 )
1#
