Controller/IOController/clock_divider.v
module clock_divider(
    sysclk, 		// System Clock Input 100 Mhz
    sysclkfreq,
    divclkfreq,
    divclk);

    input [63:0] sysclkfreq;
    input [63:0] divclkfreq;
    input sysclk;

    output divclk;

    wire[64:0] CounterLimit;
    reg divided_clk = 0;
    reg[64:0] counter = 0;
    
    assign CounterLimit = (sysclkfreq / (2 * divclkfreq)) - 1;
    
    always @(posedge sysclk) begin
       if(counter < CounterLimit)
           counter <= counter + 1;
       else begin
           counter <= 0;    
           divided_clk <= ~divided_clk;
       end
    end

    assign divclk = divided_clk;
    
endmodule

CPU/InstructionBuilder/frame_rdy_instructionbuilder.v
// puts a 1 indicator inside reg $29 (indicates the jump button has just been pressed)

module frame_rdy_instructionbuilder(instruction);

    output [31:0] instruction;

    // opcode = 00101 (addi)
    assign instruction[31:27] = 5'd5;

    // rd = 29
    assign instruction[26:22] = 5'd28;

    // rs = 0
    assign instruction[21:17] = 5'b0;

    // 17 bit immediate = 1
    assign instruction[16:0] = 17'b1;

endmodule

CPU/InstructionBuilder/jump_key_input_instructionbuilder.v
// puts a 1 indicator inside reg $29 (indicates the jump button has just been pressed)

module jump_key_input_instructionbuilder(instruction);

    output [31:0] instruction;

    // opcode = 00101 (addi)
    assign instruction[31:27] = 5'd5;

    // rd = 29
    assign instruction[26:22] = 5'd29;

    // rs = 0
    assign instruction[21:17] = 5'b0;

    // 17 bit immediate = 1
    assign instruction[16:0] = 17'b1;

endmodule

Controller/IOController/InputController.v
module InputController(interrupt_instrucion, jump_key, frame_rt_clk, sysclk, reset);

    input frame_rt_clk, sysclk, reset, jump_key;
    output [31:0] interrupt_instrucion;

    // reads from different registers at frame rate, compares contents

    reg key_interrupt_reg = 0;
    reg next_frame_rdy = 0;

    always @(posedge frame_rt_clk or posedge reset) begin
        next_frame_rdy <= 1;
        if(reset) begin
            key_interrupt_reg <= 0;
        end else begin
            if (jump_key) begin
                key_interrupt_reg <= 1;
            end
        end
    end

    // turns off key_interrupt_reg as soon as possible (1 sys clock cycle after the frame rate rises)
    // so that only one interrupt instruction is sent to CPU

    always @(negedge sysclk) begin

        if (key_interrupt_reg) begin
            key_interrupt_reg <= 0;
        end
        if (next_frame_rdy) begin
            next_frame_rdy <= 0;
        end
    end

    wire [31:0] input_instruction, frame_rdy_instruction;

    jump_key_input_instructionbuilder jump_inst_builder(.instruction(input_instruction));
    frame_rdy_instructionbuilder frame_rdy_inst_builder(.instruction(frame_rdy_instruction));

    assign interrupt_instrucion = key_interrupt_reg != 32'b0 ? input_instruction :
                                  next_frame_rdy != 32'b0 ? frame_rdy_instruction :
                                  32'b0;


endmodule

Controller/IOController/InputControllerTB.v
`timescale 1ns/100ps
module InputControllerTB;

    // module inputs
    reg clock = 0;
    reg jump = 1;

    // output
    wire frame_rate_clk;

    wire [31:0] interrupt_instruction;

    // definitions

    localparam MHz = 1000000;
    localparam SYSTEM_FREQ = 100*MHz; // System clock frequency

    localparam GAME_FRAME_RT = 10*MHz;

    InputController input_controller(.interrupt_instrucion(interrupt_instruction), .jump_key(jump),
                                    .frame_rt_clk(frame_rate_clk), .sysclk(clock),
                                    .reset(1'b0));

    clock_divider frame_rate_clock_divider(.divclk(frame_rate_clk), .divclkfreq(GAME_FRAME_RT),
                                           .sysclk(clock), .sysclkfreq(SYSTEM_FREQ));

	integer i = 0;

	initial begin

        @(posedge clock);

        begin
            for (i = 0; i < 10000000; i = i + 1) begin

            end

            @(posedge clock);
		end

        $dumpfile("InputControllerTB.vcd");
        // Module to capture and what level, 0 means all wires
        $dumpvars(0, InputControllerTB);

		#1000;
		$finish;
	end

    always
    	#10 clock = !clock;

endmodule

InputControllerTB.vcd
$date
	Sun Nov 14 16:35:51 2021
$end
$version
	Icarus Verilog
$end
$timescale
	1ps
$end
$scope module InputControllerTB $end
$var wire 32 ! interrupt_instruction [31:0] $end
$var wire 1 " frame_rate_clk $end
$var reg 1 # clock $end
$var reg 1 $ jump $end
$var integer 32 % i [31:0] $end
$scope module frame_rate_clock_divider $end
$var wire 1 " divclk $end
$var wire 64 & divclkfreq [63:0] $end
$var wire 1 # sysclk $end
$var wire 64 ' sysclkfreq [63:0] $end
$var wire 65 ( CounterLimit [64:0] $end
$var reg 65 ) counter [64:0] $end
$var reg 1 * divided_clk $end
$upscope $end
$scope module input_controller $end
$var wire 1 " frame_rt_clk $end
$var wire 1 $ jump_key $end
$var wire 1 + reset $end
$var wire 1 # sysclk $end
$var wire 32 , interrupt_instrucion [31:0] $end
$var wire 32 - input_instruction [31:0] $end
$var wire 32 . frame_rdy_instruction [31:0] $end
$var reg 1 / key_interrupt_reg $end
$var reg 1 0 next_frame_rdy $end
$scope module frame_rdy_inst_builder $end
$var wire 32 1 instruction [31:0] $end
$upscope $end
$scope module jump_inst_builder $end
$var wire 32 2 instruction [31:0] $end
$upscope $end
$upscope $end
$upscope $end
$enddefinitions $end
#30000
$dumpvars
b101111010000000000000000000001 2
b101111000000000000000000000001 1
00
0/
b101111000000000000000000000001 .
b101111010000000000000000000001 -
b0 ,
0+
0*
b10 )
b100 (
b101111101011110000100000000 '
b100110001001011010000000 &
b100110001001011010000000 %
1$
1#
0"
b0 !
$end
#40000
0#
#50000
b11 )
1#
#60000
0#
#70000
b100 )
1#
#80000
0#
#90000
b101111010000000000000000000001 !
b101111010000000000000000000001 ,
1/
10
1"
1*
b0 )
1#
#100000
b0 !
b0 ,
00
0/
0#
#110000
b1 )
1#
#120000
0#
#130000
b10 )
1#
#140000
0#
#150000
b11 )
1#
#160000
0#
#170000
b100 )
1#
#180000
0#
#190000
0"
0*
b0 )
1#
#200000
0#
#210000
b1 )
1#
#220000
0#
#230000
b10 )
1#
#240000
0#
#250000
b11 )
1#
#260000
0#
#270000
b100 )
1#
#280000
0#
#290000
b101111010000000000000000000001 !
b101111010000000000000000000001 ,
1/
10
1"
1*
b0 )
1#
#300000
b0 !
b0 ,
00
0/
0#
#310000
b1 )
1#
#320000
0#
#330000
b10 )
1#
#340000
0#
#350000
b11 )
1#
#360000
0#
#370000
b100 )
1#
#380000
0#
#390000
0"
0*
b0 )
1#
#400000
0#
#410000
b1 )
1#
#420000
0#
#430000
b10 )
1#
#440000
0#
#450000
b11 )
1#
#460000
0#
#470000
b100 )
1#
#480000
0#
#490000
b101111010000000000000000000001 !
b101111010000000000000000000001 ,
1/
10
1"
1*
b0 )
1#
#500000
b0 !
b0 ,
00
0/
0#
#510000
b1 )
1#
#520000
0#
#530000
b10 )
1#
#540000
0#
#550000
b11 )
1#
#560000
0#
#570000
b100 )
1#
#580000
0#
#590000
0"
0*
b0 )
1#
#600000
0#
#610000
b1 )
1#
#620000
0#
#630000
b10 )
1#
#640000
0#
#650000
b11 )
1#
#660000
0#
#670000
b100 )
1#
#680000
0#
#690000
b101111010000000000000000000001 !
b101111010000000000000000000001 ,
1/
10
1"
1*
b0 )
1#
#700000
b0 !
b0 ,
00
0/
0#
#710000
b1 )
1#
#720000
0#
#730000
b10 )
1#
#740000
0#
#750000
b11 )
1#
#760000
0#
#770000
b100 )
1#
#780000
0#
#790000
0"
0*
b0 )
1#
#800000
0#
#810000
b1 )
1#
#820000
0#
#830000
b10 )
1#
#840000
0#
#850000
b11 )
1#
#860000
0#
#870000
b100 )
1#
#880000
0#
#890000
b101111010000000000000000000001 !
b101111010000000000000000000001 ,
1/
10
1"
1*
b0 )
1#
#900000
b0 !
b0 ,
00
0/
0#
#910000
b1 )
1#
#920000
0#
#930000
b10 )
1#
#940000
0#
#950000
b11 )
1#
#960000
0#
#970000
b100 )
1#
#980000
0#
#990000
0"
0*
b0 )
1#
#1000000
0#
#1010000
b1 )
1#
#1020000
0#
#1030000
b10 )
1#
