Controller/IOController/clock_divider.v
module clock_divider(
    sysclk, 		// System Clock Input 100 Mhz
    sysclkfreq,
    divclkfreq,
    divclk);

    input [63:0] sysclkfreq;
    input [63:0] divclkfreq;
    input sysclk;

    output divclk;

    wire[64:0] CounterLimit;
    reg divided_clk = 0;
    reg[64:0] counter = 0;
    
    assign CounterLimit = (sysclkfreq / (2 * divclkfreq)) - 1;
    
    always @(posedge sysclk) begin
       if(counter < CounterLimit)
           counter <= counter + 1;
       else begin
           counter <= 0;    
           divided_clk <= ~divided_clk;
       end
    end

    assign divclk = divided_clk;
    
endmodule

Controller/IOController/frame_rdy_instructionbuilder.v
// puts a 1 indicator inside reg $29 (indicates the jump button has just been pressed)

module frame_rdy_instructionbuilder(instruction);

    output [31:0] instruction;

    // opcode = 00101 (addi)
    assign instruction[31:27] = 5'd5;

    // rd = 28
    assign instruction[26:22] = 5'd28;

    // rs = 0
    assign instruction[21:17] = 5'b0;

    // 17 bit immediate = 1
    assign instruction[16:0] = 17'b1;

endmodule

CPU/InstructionBuilder/jump_key_input_instructionbuilder.v
// puts a 1 indicator inside reg $29 (indicates the jump button has just been pressed)

module jump_key_input_instructionbuilder(instruction);

    output [31:0] instruction;

    // opcode = 00101 (addi)
    assign instruction[31:27] = 5'd5;

    // rd = 29
    assign instruction[26:22] = 5'd29;

    // 17 bit immediate = 1
    assign instruction[16:0] = 17'b1;

endmodule

Controller/IOController/JumpController.v
module JumpController(frame_rt_clk, proc_clk, reset, can_jump);

    input frame_rt_clk, proc_clk, reset;
    output can_jump; 

    // reads from different registers at frame rate, compares contents

    wire[31:0] CounterLimit;
    reg[31:0] counter = 0;
    reg jump_reg=0; 
    assign can_jump=jump_reg; 

    //localparam MHz = 5;
    //localparam PROC_FREQ = 20*MHz;
    //localparam BUTTON_RT = 10; // 60 fps
    localparam EmpiricalParam= 10; 
   
    assign CounterLimit = EmpiricalParam-4;

    always @(posedge proc_clk or posedge reset) begin
        if(reset) begin
            counter <= 0;
        end
        else begin 
            if (counter < CounterLimit) begin
                counter <= counter + 1;
                if (counter<3) 
                    jump_reg<=1;
                else begin 
                    jump_reg<=0; 
                end 
            end 
            else begin
                    counter <= 0;
            end 
        end
    end 

endmodule

Controller/IOController/InputController.v
module InputController(interrupt_instrucion, jump_key, frame_rt_clk, proc_clk, reset);

    input frame_rt_clk, proc_clk, reset, jump_key;
    output [31:0] interrupt_instrucion;

    // reads from different registers at frame rate, compares contents

    wire[31:0] CounterLimit;
    reg[31:0] counter = 0;

    localparam MHz = 1000000;
    localparam PROC_FREQ = 50*MHz;

    localparam GAME_FRAME_RT = 60; // 60 fps
   
    assign CounterLimit = (PROC_FREQ / GAME_FRAME_RT) - 1;
   
    reg key_interrupt_reg, next_frame_rdy = 0;

    always @(posedge proc_clk or posedge reset) begin
        if(reset) begin
            key_interrupt_reg <= 0;
        end else begin
            // turn off key_interrupt and next_frame_rdy signal as soon as the counter resets so that interrupt signal only sent for 1 proc cycle
            if (counter < CounterLimit) begin
                if (key_interrupt_reg || next_frame_rdy) begin
                    key_interrupt_reg <= 0;
                    next_frame_rdy <= 0;
                end
                counter <= counter + 1;
            end else begin
                next_frame_rdy <= 1;
                counter <= 0;
                if (jump_key) begin
                    key_interrupt_reg <= 1;
                end
            end
        end
    end

    JumpController jumper(frame_rt_clk, proc_clk, reset, can_jump);
    wire can_jump; 

    wire [31:0] input_instruction, frame_rdy_instruction;

    jump_key_input_instructionbuilder jump_inst_builder(.instruction(input_instruction));
    frame_rdy_instructionbuilder frame_rdy_inst_builder(.instruction(frame_rdy_instruction));

    wire allow_interrupt; 
    assign allow_interrupt= ((key_interrupt_reg != 1'b0) && can_jump); 

    assign interrupt_instrucion = ((key_interrupt_reg != 1'b0) && can_jump) ? input_instruction :
                                  next_frame_rdy != 1'b0 ? frame_rdy_instruction :
                                  32'b0;


endmodule

Controller/IOController/InputControllerTB.v
`timescale 1ns/100ps
module InputControllerTB;

    // module inputs
    reg clock = 0;
    reg jump = 1;

    // output
    wire frame_rate_clk, proc_clk;

    wire [31:0] interrupt_instruction;

    // definitions

    localparam MHz = 1000000;

    localparam SYSTEM_FREQ = 100*MHz; // System clock frequency
    localparam PROC_FREQ = 50*MHz; // System clock frequency

    localparam GAME_FRAME_RT = 64'd60;

    InputController input_controller(.interrupt_instrucion(interrupt_instruction), .jump_key(jump),
                                    .frame_rt_clk(frame_rate_clk), .proc_clk(clock),
                                    .reset(1'b0));

    clock_divider proc_clock_divider(.divclk(proc_clk), .divclkfreq(PROC_FREQ),
                                           .sysclk(clock), .sysclkfreq(SYSTEM_FREQ));

    clock_divider frame_rate_clock_divider(.divclk(frame_rate_clk), .divclkfreq(GAME_FRAME_RT),
                                           .sysclk(proc_clk), .sysclkfreq(PROC_FREQ));


	integer i = 0;

	initial begin

        @(posedge clock);

        begin
            for (i = 0; i < 10000000; i = i + 1) begin

            end

            @(posedge clock);
		end

        $dumpfile("InputControllerTB.vcd");
        // Module to capture and what level, 0 means all wires
        $dumpvars(0, InputControllerTB);

		#1000;
		$finish;
	end

    always
    	#10 clock = !clock;

endmodule

Controller/IOController/InputControllerTB.vcd
$date
	Mon Nov 29 14:01:30 2021
$end
$version
	Icarus Verilog
$end
$timescale
	100ps
$end
$scope module InputControllerTB $end
$var wire 1 ! proc_clk $end
$var wire 32 " interrupt_instruction [31:0] $end
$var wire 1 # frame_rate_clk $end
$var reg 1 $ clock $end
$var reg 1 % jump $end
$var integer 32 & i [31:0] $end
$scope module frame_rate_clock_divider $end
$var wire 1 # divclk $end
$var wire 64 ' divclkfreq [63:0] $end
$var wire 64 ( sysclkfreq [63:0] $end
$var wire 1 ! sysclk $end
$var wire 65 ) CounterLimit [64:0] $end
$var reg 65 * counter [64:0] $end
$var reg 1 + divided_clk $end
$upscope $end
$scope module input_controller $end
$var wire 32 , CounterLimit [31:0] $end
$var wire 1 - allow_interrupt $end
$var wire 1 # frame_rt_clk $end
$var wire 1 % jump_key $end
$var wire 1 $ proc_clk $end
$var wire 1 . reset $end
$var wire 32 / interrupt_instrucion [31:0] $end
$var wire 32 0 input_instruction [31:0] $end
$var wire 32 1 frame_rdy_instruction [31:0] $end
$var wire 1 2 can_jump $end
$var reg 32 3 counter [31:0] $end
$var reg 1 4 key_interrupt_reg $end
$var reg 1 5 next_frame_rdy $end
$scope module frame_rdy_inst_builder $end
$var wire 32 6 instruction [31:0] $end
$upscope $end
$scope module jump_inst_builder $end
$var wire 32 7 instruction [31:0] $end
$upscope $end
$scope module jumper $end
$var wire 32 8 CounterLimit [31:0] $end
$var wire 1 # frame_rt_clk $end
$var wire 1 $ proc_clk $end
$var wire 1 . reset $end
$var wire 1 2 can_jump $end
$var reg 32 9 counter [31:0] $end
$var reg 1 2 jump_reg $end
$upscope $end
$upscope $end
$scope module proc_clock_divider $end
$var wire 1 ! divclk $end
$var wire 64 : divclkfreq [63:0] $end
$var wire 1 $ sysclk $end
$var wire 64 ; sysclkfreq [63:0] $end
$var wire 65 < CounterLimit [64:0] $end
$var reg 65 = counter [64:0] $end
$var reg 1 > divided_clk $end
$upscope $end
$upscope $end
$enddefinitions $end
#300
$dumpvars
0>
b0 =
b0 <
b101111101011110000100000000 ;
b10111110101111000010000000 :
b10 9
b10100 8
b101111010000000000000000000001 7
b101111000000000000000000000001 6
05
04
b10 3
12
b101111000000000000000000000001 1
b101111010000000000000000000001 0
b0 /
0.
0-
b11001011011100110100 ,
0+
b1 *
b1100101101110011001 )
b10111110101111000010000000 (
b111100 '
b100110001001011010000000 &
1%
1$
0#
b0 "
0!
$end
#400
0$
#500
b10 *
b11 9
b11 3
1!
1>
1$
#600
0$
#700
b100 3
b100 9
0!
0>
1$
#800
0$
#900
b11 *
b101 9
b101 3
1!
1>
1$
#1000
0$
#1100
b110 3
02
b110 9
0!
0>
1$
#1200
0$
#1300
b100 *
b111 9
b111 3
1!
1>
1$
#1400
0$
#1500
b1000 3
b1000 9
0!
0>
1$
#1600
0$
#1700
b101 *
b1001 9
b1001 3
1!
1>
1$
#1800
0$
#1900
b1010 3
b1010 9
0!
0>
1$
#2000
0$
#2100
b110 *
b1011 9
b1011 3
1!
1>
1$
#2200
0$
#2300
b1100 3
b1100 9
0!
0>
1$
#2400
0$
#2500
b111 *
b1101 9
b1101 3
1!
1>
1$
#2600
0$
#2700
b1110 3
b1110 9
0!
0>
1$
#2800
0$
#2900
b1000 *
b1111 9
b1111 3
1!
1>
1$
#3000
0$
#3100
b10000 3
b10000 9
0!
0>
1$
#3200
0$
#3300
b1001 *
b10001 9
b10001 3
1!
1>
1$
#3400
0$
#3500
b10010 3
b10010 9
0!
0>
1$
#3600
0$
#3700
b1010 *
b10011 9
b10011 3
1!
1>
1$
#3800
0$
#3900
b10100 3
b10100 9
0!
0>
1$
#4000
0$
#4100
b1011 *
b0 9
b10101 3
1!
1>
1$
#4200
0$
#4300
b10110 3
12
b1 9
0!
0>
1$
#4400
0$
#4500
b1100 *
b10 9
b10111 3
1!
1>
1$
#4600
0$
#4700
b11000 3
b11 9
0!
0>
1$
#4800
0$
#4900
b1101 *
b100 9
b11001 3
1!
1>
1$
#5000
0$
#5100
b11010 3
b101 9
0!
0>
1$
#5200
0$
#5300
b1110 *
02
b110 9
b11011 3
1!
1>
1$
#5400
0$
#5500
b11100 3
b111 9
0!
0>
1$
#5600
0$
#5700
b1111 *
b1000 9
b11101 3
1!
1>
1$
#5800
0$
#5900
b11110 3
b1001 9
0!
0>
1$
#6000
0$
#6100
b10000 *
b1010 9
b11111 3
1!
1>
1$
#6200
0$
#6300
b100000 3
b1011 9
0!
0>
1$
#6400
0$
#6500
b10001 *
b1100 9
b100001 3
1!
1>
1$
#6600
0$
#6700
b100010 3
b1101 9
0!
0>
1$
#6800
0$
#6900
b10010 *
b1110 9
b100011 3
1!
1>
1$
#7000
0$
#7100
b100100 3
b1111 9
0!
0>
1$
#7200
0$
#7300
b10011 *
b10000 9
b100101 3
1!
1>
1$
#7400
0$
#7500
b100110 3
b10001 9
0!
0>
1$
#7600
0$
#7700
b10100 *
b10010 9
b100111 3
1!
1>
1$
#7800
0$
#7900
b101000 3
b10011 9
0!
0>
1$
#8000
0$
#8100
b10101 *
b10100 9
b101001 3
1!
1>
1$
#8200
0$
#8300
b101010 3
b0 9
0!
0>
1$
#8400
0$
#8500
b10110 *
12
b1 9
b101011 3
1!
1>
1$
#8600
0$
#8700
b101100 3
b10 9
0!
0>
1$
#8800
0$
#8900
b10111 *
b11 9
b101101 3
1!
1>
1$
#9000
0$
#9100
b101110 3
b100 9
0!
0>
1$
#9200
0$
#9300
b11000 *
b101 9
b101111 3
1!
1>
1$
#9400
0$
#9500
b110000 3
02
b110 9
0!
0>
1$
#9600
0$
#9700
b11001 *
b111 9
b110001 3
1!
1>
1$
#9800
0$
#9900
b110010 3
b1000 9
0!
0>
1$
#10000
0$
#10100
b11010 *
b1001 9
b110011 3
1!
1>
1$
#10200
0$
#10300
b110100 3
b1010 9
0!
0>
1$
