Controller/IOController/clock_divider.v
module clock_divider(
    sysclk, 		// System Clock Input 100 Mhz
    sysclkfreq,
    divclkfreq,
    divclk);

    input [63:0] sysclkfreq;
    input [63:0] divclkfreq;
    input sysclk;

    output divclk;

    wire[64:0] CounterLimit;
    reg divided_clk = 0;
    reg[64:0] counter = 0;
    
    assign CounterLimit = (sysclkfreq / (2 * divclkfreq)) - 1;
    
    always @(posedge sysclk) begin
       if(counter < CounterLimit)
           counter <= counter + 1;
       else begin
           counter <= 0;    
           divided_clk <= ~divided_clk;
       end
    end

    assign divclk = divided_clk;
    
endmodule

Controller/IOController/frame_rdy_instructionbuilder.v
// puts a 1 indicator inside reg $29 (indicates the jump button has just been pressed)

module frame_rdy_instructionbuilder(instruction);

    output [31:0] instruction;

    // opcode = 00101 (addi)
    assign instruction[31:27] = 5'd5;

    // rd = 28
    assign instruction[26:22] = 5'd28;

    // rs = 0
    assign instruction[21:17] = 5'b0;

    // 17 bit immediate = 1
    assign instruction[16:0] = 17'b1;

endmodule

CPU/InstructionBuilder/jump_key_input_instructionbuilder.v
// puts a 1 indicator inside reg $29 (indicates the jump button has just been pressed)

module jump_key_input_instructionbuilder(instruction);

    output [31:0] instruction;

    // opcode = 00101 (addi)
    assign instruction[31:27] = 5'd5;

    // rd = 29
    assign instruction[26:22] = 5'd29;

    // 17 bit immediate = 1
    assign instruction[16:0] = 17'b1;

endmodule

Controller/IOController/InputController.v
module InputController(interrupt_instrucion, jump_key, frame_rt_clk, proc_clk, reset);

    input frame_rt_clk, proc_clk, reset, jump_key;
    output [31:0] interrupt_instrucion;

    // reads from different registers at frame rate, compares contents

    wire[64:0] CounterLimit;
    reg[64:0] counter = 0;

    localparam MHz = 1000000;
    localparam PROC_FREQ = 50*MHz;

    localparam GAME_FRAME_RT = 64'd60; // 60 fps

    assign CounterLimit = (PROC_FREQ / GAME_FRAME_RT) - 1;

    reg key_interrupt_reg = 0;
    reg next_frame_rdy = 0;

    always @(posedge proc_clk or posedge reset) begin
        if(reset) begin
            key_interrupt_reg <= 0;
        end
        else begin
            // turn off key_interrupt and next_frame_rdy signal as soon as the counter resets so that interrupt signal only sent for 1 proc cycle
            if (counter < CounterLimit) begin
                if (key_interrupt_reg || next_frame_rdy) begin
                    key_interrupt_reg <= 0;
                    next_frame_rdy <= 0;
                end
                counter <= counter + 1;
            end else begin
                next_frame_rdy <= 1;
                counter <= 0;
                if (jump_key) begin
                    key_interrupt_reg <= 1;
                end
            end
        end
    end


    // turns off key_interrupt_reg as soon as possible (1 sys clock cycle after the frame rate rises)
    // so that only one interrupt instruction is sent to CPU

//    always @(posedge proc_clk) begin
//
//        if (key_interrupt_reg) begin
//            key_interrupt_reg <= 0;
//        end
//        if (next_frame_rdy) begin
//            next_frame_rdy <= 0;
//        end
//    end

    wire [31:0] input_instruction, frame_rdy_instruction;

    jump_key_input_instructionbuilder jump_inst_builder(.instruction(input_instruction));
    frame_rdy_instructionbuilder frame_rdy_inst_builder(.instruction(frame_rdy_instruction));

    assign interrupt_instrucion = key_interrupt_reg != 1'b0 ? input_instruction :
                                  next_frame_rdy != 1'b0 ? frame_rdy_instruction :
                                  32'b0;


endmodule

Controller/IOController/InputControllerTB.v
`timescale 1ns/100ps
module InputControllerTB;

    // module inputs
    reg clock = 0;
    reg jump = 1;

    // output
    wire frame_rate_clk, proc_clk;

    wire [31:0] interrupt_instruction;

    // definitions

    localparam MHz = 1000000;

    localparam SYSTEM_FREQ = 100*MHz; // System clock frequency
    localparam PROC_FREQ = 50*MHz; // System clock frequency

    localparam GAME_FRAME_RT = 10*MHz;

    InputController input_controller(.interrupt_instrucion(interrupt_instruction), .jump_key(jump),
                                    .frame_rt_clk(frame_rate_clk), .proc_clk(clock),
                                    .reset(1'b0));

    clock_divider proc_clock_divider(.divclk(proc_clk), .divclkfreq(PROC_FREQ),
                                           .sysclk(clock), .sysclkfreq(SYSTEM_FREQ));

    clock_divider frame_rate_clock_divider(.divclk(frame_rate_clk), .divclkfreq(GAME_FRAME_RT),
                                           .sysclk(proc_clk), .sysclkfreq(PROC_FREQ));


	integer i = 0;

	initial begin

        @(posedge clock);

        begin
            for (i = 0; i < 10000000; i = i + 1) begin

            end

            @(posedge clock);
		end

        $dumpfile("InputControllerTB.vcd");
        // Module to capture and what level, 0 means all wires
        $dumpvars(0, InputControllerTB);

		#1000;
		$finish;
	end

    always
    	#10 clock = !clock;

endmodule

Controller/IOController/InputControllerTB.vcd
$date
	Sun Nov 28 12:54:47 2021
$end
$version
	Icarus Verilog
$end
$timescale
	1ps
$end
$scope module InputControllerTB $end
$var wire 1 ! proc_clk $end
$var wire 32 " interrupt_instruction [31:0] $end
$var wire 1 # frame_rate_clk $end
$var reg 1 $ clock $end
$var reg 1 % jump $end
$var integer 32 & i [31:0] $end
$scope module frame_rate_clock_divider $end
$var wire 1 # divclk $end
$var wire 64 ' divclkfreq [63:0] $end
$var wire 64 ( sysclkfreq [63:0] $end
$var wire 1 ! sysclk $end
$var wire 65 ) CounterLimit [64:0] $end
$var reg 65 * counter [64:0] $end
$var reg 1 + divided_clk $end
$upscope $end
$scope module input_controller $end
$var wire 65 , CounterLimit [64:0] $end
$var wire 1 # frame_rt_clk $end
$var wire 1 % jump_key $end
$var wire 1 $ proc_clk $end
$var wire 1 - reset $end
$var wire 32 . interrupt_instrucion [31:0] $end
$var wire 32 / input_instruction [31:0] $end
$var wire 32 0 frame_rdy_instruction [31:0] $end
$var reg 65 1 counter [64:0] $end
$var reg 1 2 key_interrupt_reg $end
$var reg 1 3 next_frame_rdy $end
$scope module frame_rdy_inst_builder $end
$var wire 32 4 instruction [31:0] $end
$upscope $end
$scope module jump_inst_builder $end
$var wire 32 5 instruction [31:0] $end
$upscope $end
$upscope $end
$scope module proc_clock_divider $end
$var wire 1 ! divclk $end
$var wire 64 6 divclkfreq [63:0] $end
$var wire 1 $ sysclk $end
$var wire 64 7 sysclkfreq [63:0] $end
$var wire 65 8 CounterLimit [64:0] $end
$var reg 65 9 counter [64:0] $end
$var reg 1 : divided_clk $end
$upscope $end
$upscope $end
$enddefinitions $end
#30000
$dumpvars
0:
b0 9
b0 8
b101111101011110000100000000 7
b10111110101111000010000000 6
b101111010000000000000000000001 5
b101111000000000000000000000001 4
13
12
b0 1
b101111000000000000000000000001 0
b101111010000000000000000000001 /
b101111010000000000000000000001 .
0-
b1 ,
0+
b1 *
b1 )
b10111110101111000010000000 (
b100110001001011010000000 '
b100110001001011010000000 &
1%
1$
0#
b101111010000000000000000000001 "
0!
$end
#40000
0$
#50000
1#
1+
b0 *
b0 "
b0 .
b1 1
03
02
1!
1:
1$
#60000
0$
#70000
b101111010000000000000000000001 "
b101111010000000000000000000001 .
12
b0 1
13
0!
0:
1$
#80000
0$
#90000
b1 *
b0 "
b0 .
b1 1
03
02
1!
1:
1$
#100000
0$
#110000
b101111010000000000000000000001 "
b101111010000000000000000000001 .
12
b0 1
13
0!
0:
1$
#120000
0$
#130000
0#
0+
b0 *
b0 "
b0 .
b1 1
03
02
1!
1:
1$
#140000
0$
#150000
b101111010000000000000000000001 "
b101111010000000000000000000001 .
12
b0 1
13
0!
0:
1$
#160000
0$
#170000
b1 *
b0 "
b0 .
b1 1
03
02
1!
1:
1$
#180000
0$
#190000
b101111010000000000000000000001 "
b101111010000000000000000000001 .
12
b0 1
13
0!
0:
1$
#200000
0$
#210000
1#
1+
b0 *
b0 "
b0 .
b1 1
03
02
1!
1:
1$
#220000
0$
#230000
b101111010000000000000000000001 "
b101111010000000000000000000001 .
12
b0 1
13
0!
0:
1$
#240000
0$
#250000
b1 *
b0 "
b0 .
b1 1
03
02
1!
1:
1$
#260000
0$
#270000
b101111010000000000000000000001 "
b101111010000000000000000000001 .
12
b0 1
13
0!
0:
1$
#280000
0$
#290000
0#
0+
b0 *
b0 "
b0 .
b1 1
03
02
1!
1:
1$
#300000
0$
#310000
b101111010000000000000000000001 "
b101111010000000000000000000001 .
12
b0 1
13
0!
0:
1$
#320000
0$
#330000
b1 *
b0 "
b0 .
b1 1
03
02
1!
1:
1$
#340000
0$
#350000
b101111010000000000000000000001 "
b101111010000000000000000000001 .
12
b0 1
13
0!
0:
1$
#360000
0$
#370000
1#
1+
b0 *
b0 "
b0 .
b1 1
03
02
1!
1:
1$
#380000
0$
#390000
b101111010000000000000000000001 "
b101111010000000000000000000001 .
12
b0 1
13
0!
0:
1$
#400000
0$
#410000
b1 *
b0 "
b0 .
b1 1
03
02
1!
1:
1$
#420000
0$
#430000
b101111010000000000000000000001 "
b101111010000000000000000000001 .
12
b0 1
13
0!
0:
1$
#440000
0$
#450000
0#
0+
b0 *
b0 "
b0 .
b1 1
03
02
1!
1:
1$
#460000
0$
#470000
b101111010000000000000000000001 "
b101111010000000000000000000001 .
12
b0 1
13
0!
0:
1$
#480000
0$
#490000
b1 *
b0 "
b0 .
b1 1
03
02
1!
1:
1$
#500000
0$
#510000
b101111010000000000000000000001 "
b101111010000000000000000000001 .
12
b0 1
13
0!
0:
1$
#520000
0$
#530000
1#
1+
b0 *
b0 "
b0 .
b1 1
03
02
1!
1:
1$
#540000
0$
#550000
b101111010000000000000000000001 "
b101111010000000000000000000001 .
12
b0 1
13
0!
0:
1$
#560000
0$
#570000
b1 *
b0 "
b0 .
b1 1
03
02
1!
1:
1$
#580000
0$
#590000
b101111010000000000000000000001 "
b101111010000000000000000000001 .
12
b0 1
13
0!
0:
1$
#600000
0$
#610000
0#
0+
b0 *
b0 "
b0 .
b1 1
03
02
1!
1:
1$
#620000
0$
#630000
b101111010000000000000000000001 "
b101111010000000000000000000001 .
12
b0 1
13
0!
0:
1$
#640000
0$
#650000
b1 *
b0 "
b0 .
b1 1
03
02
1!
1:
1$
#660000
0$
#670000
b101111010000000000000000000001 "
b101111010000000000000000000001 .
12
b0 1
13
0!
0:
1$
#680000
0$
#690000
1#
1+
b0 *
b0 "
b0 .
b1 1
03
02
1!
1:
1$
#700000
0$
#710000
b101111010000000000000000000001 "
b101111010000000000000000000001 .
12
b0 1
13
0!
0:
1$
#720000
0$
#730000
b1 *
b0 "
b0 .
b1 1
03
02
1!
1:
1$
#740000
0$
#750000
b101111010000000000000000000001 "
b101111010000000000000000000001 .
12
b0 1
13
0!
0:
1$
#760000
0$
#770000
0#
0+
b0 *
b0 "
b0 .
b1 1
03
02
1!
1:
1$
#780000
0$
#790000
b101111010000000000000000000001 "
b101111010000000000000000000001 .
12
b0 1
13
0!
0:
1$
#800000
0$
#810000
b1 *
b0 "
b0 .
b1 1
03
02
1!
1:
1$
#820000
0$
#830000
b101111010000000000000000000001 "
b101111010000000000000000000001 .
12
b0 1
13
0!
0:
1$
#840000
0$
#850000
1#
1+
b0 *
b0 "
b0 .
b1 1
03
02
1!
1:
1$
#860000
0$
#870000
b101111010000000000000000000001 "
b101111010000000000000000000001 .
12
b0 1
13
0!
0:
1$
#880000
0$
#890000
b1 *
b0 "
b0 .
b1 1
03
02
1!
1:
1$
#900000
0$
#910000
b101111010000000000000000000001 "
b101111010000000000000000000001 .
12
b0 1
13
0!
0:
1$
#920000
0$
#930000
0#
0+
b0 *
b0 "
b0 .
b1 1
03
02
1!
1:
1$
#940000
0$
#950000
b101111010000000000000000000001 "
b101111010000000000000000000001 .
12
b0 1
13
0!
0:
1$
#960000
0$
#970000
b1 *
b0 "
b0 .
b1 1
03
02
1!
1:
1$
#980000
0$
#990000
b101111010000000000000000000001 "
b101111010000000000000000000001 .
12
b0 1
13
0!
0:
1$
#1000000
0$
#1010000
1#
1+
b0 *
b0 "
b0 .
b1 1
03
02
1!
1:
1$
#1020000
0$
#1030000
b101111010000000000000000000001 "
b101111010000000000000000000001 .
12
b0 1
13
0!
0:
1$
